slurm_sweeps/__init__.py
slurm_sweeps/asha.py
slurm_sweeps/backend.py
slurm_sweeps/constants.py
slurm_sweeps/database.py
slurm_sweeps/experiment.py
slurm_sweeps/logger.py
slurm_sweeps/sampler.py
slurm_sweeps/storage.py
slurm_sweeps/trial.py
slurm_sweeps/integrations/__init__.py
slurm_sweeps/integrations/lightning.py
slurm_sweeps-0.1.3.dist-info/LICENSE
slurm_sweeps-0.1.3.dist-info/METADATA
slurm_sweeps-0.1.3.dist-info/WHEEL
slurm_sweeps-0.1.3.dist-info/top_level.txt
slurm_sweeps-0.1.3.dist-info/RECORD
