Metadata-Version: 2.1
Name: slurm-sweeps
Version: 0.1.3
Summary: A simple tool to perform sweeps on SLURM clusters.
Requires-Python: >=3.8
License-File: LICENSE
Requires-Dist: cloudpickle
Requires-Dist: numpy
Requires-Dist: pandas
Requires-Dist: pyyaml
